bd_geoinfo/__init__.py
bd_geoinfo/districts.py
bd_geoinfo/divisions.py
bd_geoinfo/postcodes.py
bd_geoinfo/terminal.html
bd_geoinfo/terminal.py
bd_geoinfo/unions.py
bd_geoinfo/upzilas.py
bd_geoinfo/data/districts.json
bd_geoinfo/data/divisions.json
bd_geoinfo/data/postcodes.json
bd_geoinfo/data/unions.json
bd_geoinfo/data/upazilas.json
bd_geoinfo-0.0.3.dist-info/METADATA
bd_geoinfo-0.0.3.dist-info/WHEEL
bd_geoinfo-0.0.3.dist-info/top_level.txt
bd_geoinfo-0.0.3.dist-info/RECORD
