Metadata-Version: 2.4
Name: bd-geoinfo
Version: 0.0.3
Summary: A simple Python library for fetching geographical information about Bangladesh.
Home-page: https://github.com/zyxasaduzzaman/BD_GEOINFO
Author: Asaduzzaman Asad
Author-email: zyxmdasaduzzaman@gmail.com
Classifier: Programming Language :: Python :: 3
Classifier: Operating System :: OS Independent
Classifier: Topic :: Software Development :: Libraries
Classifier: Topic :: Scientific/Engineering :: GIS
Classifier: Development Status :: 3 - Alpha
Classifier: Natural Language :: Bengali
Classifier: Natural Language :: English
Requires-Python: >=3.6
Dynamic: author
Dynamic: author-email
Dynamic: classifier
Dynamic: description
Dynamic: description-content-type
Dynamic: home-page
Dynamic: requires-python
Dynamic: summary
